amosutils/__init__.py
amosutils/catalogue/__init__.py
amosutils/catalogue/catalogue.py
amosutils/classes/loadable.py
amosutils/metrics/__init__.py
amosutils/metrics/metrics.py
amosutils/physics/atmosphere.py
amosutils/physics/constants.py
amosutils/projections/__init__.py
amosutils/projections/base.py
amosutils/projections/borovicka.py
amosutils/projections/equidistant.py
amosutils/projections/koniferka.py
amosutils/projections/scalers.py
amosutils/projections/shifters.py
amosutils/projections/transformers.py
amosutils/projections/zenith.py
amosutils/trajectory/__init__.py
amosutils/trajectory/ray.py
amosutils-0.2.2.dist-info/METADATA
amosutils-0.2.2.dist-info/WHEEL
amosutils-0.2.2.dist-info/RECORD
