Metadata-Version: 2.1
Name: amosutils
Version: 0.2.2
Summary: A collection of utilitiy functions for all-sky and spectral meteor cameras
Author: Martin Baláž
Author-email: martin.balaz@fmph.uniba.sk
Requires-Python: >=3.11,<4.0
Classifier: Programming Language :: Python :: 3
Classifier: Programming Language :: Python :: 3.11
Classifier: Programming Language :: Python :: 3.12
Requires-Dist: astropy
Requires-Dist: dotmap
Requires-Dist: numpy
Requires-Dist: pandas
Requires-Dist: pyyaml
Requires-Dist: scipy
